gen_stm8/__init__.py
gen_stm8/py.typed
gen_stm8/conf/gen_stm8.cfg
gen_stm8/conf/gen_stm8.logo
gen_stm8/conf/gen_stm8_util.cfg
gen_stm8/conf/project.yaml
gen_stm8/conf/template/Makefile.template
gen_stm8/conf/template/module.template
gen_stm8/conf/template/stm8s.template
gen_stm8/log/gen_stm8.log
gen_stm8/pro/__init__.py
gen_stm8/pro/read_template.py
gen_stm8/pro/write_template.py
usr/local/bin/factory_reset.sh
usr/local/bin/gen_stm8_run.py
gen_stm8-1.4.6.dist-info/LICENSE
gen_stm8-1.4.6.dist-info/METADATA
gen_stm8-1.4.6.dist-info/WHEEL
gen_stm8-1.4.6.dist-info/top_level.txt
gen_stm8-1.4.6.dist-info/RECORD
